{"UI/Dist/Styleguide/Assets/SASS/Base/_Links.scss":[{"line":6,"column":1,"length":1,"severity":"warning","reason":"Line should be indented with spaces, not tabs","linter":"Indentation"},{"line":6,"column":2,"length":36,"severity":"warning","reason":"Colon after property should be followed by one space","linter":"SpaceAfterPropertyColon"},{"line":7,"column":1,"length":1,"severity":"warning","reason":"Files should end with a trailing newline","linter":"FinalNewline"}],"UI/Dist/Styleguide/Assets/SASS/Base/_Main.scss":[{"line":6,"column":1,"length":1,"severity":"warning","reason":"Line should be indented with spaces, not tabs","linter":"Indentation"},{"line":6,"column":2,"length":47,"severity":"warning","reason":"Colon after property should be followed by one space","linter":"SpaceAfterPropertyColon"},{"line":7,"column":1,"length":1,"severity":"warning","reason":"Line should be indented with spaces, not tabs","linter":"Indentation"},{"line":7,"column":2,"length":36,"severity":"warning","reason":"Colon after property should be followed by one space","linter":"SpaceAfterPropertyColon"},{"line":8,"column":1,"length":1,"severity":"warning","reason":"Line should be indented with spaces, not tabs","linter":"Indentation"},{"line":8,"column":2,"length":71,"severity":"warning","reason":"Colon after property should be followed by one space","linter":"SpaceAfterPropertyColon"},{"line":9,"column":1,"length":1,"severity":"warning","reason":"Files should end with a trailing newline","linter":"FinalNewline"}],"UI/Dist/Styleguide/Assets/SASS/Base/_Paragraphs.scss":[{"line":6,"column":1,"length":1,"severity":"warning","reason":"Line should be indented with spaces, not tabs","linter":"Indentation"},{"line":6,"column":2,"length":36,"severity":"warning","reason":"Colon after property should be followed by one space","linter":"SpaceAfterPropertyColon"},{"line":7,"column":1,"length":1,"severity":"warning","reason":"Files should end with a trailing newline","linter":"FinalNewline"}],"UI/Dist/Styleguide/Assets/SASS/Components/_CodePreview.scss":[{"line":6,"column":1,"length":1,"severity":"warning","reason":"Line should be indented with spaces, not tabs","linter":"Indentation"},{"line":6,"column":2,"length":30,"severity":"warning","reason":"Colon after property should be followed by one space","linter":"SpaceAfterPropertyColon"},{"line":7,"column":1,"length":1,"severity":"warning","reason":"Line should be indented with spaces, not tabs","linter":"Indentation"},{"line":7,"column":1,"length":1,"severity":"warning","reason":"Rule declaration should be preceded by an empty line","linter":"EmptyLineBetweenBlocks"},{"line":9,"column":3,"length":33,"severity":"warning","reason":"Colon after property should be followed by one space","linter":"SpaceAfterPropertyColon"},{"line":10,"column":3,"length":23,"severity":"warning","reason":"Colon after property should be followed by one space","linter":"SpaceAfterPropertyColon"},{"line":12,"column":1,"length":1,"severity":"warning","reason":"Files should end with a trailing newline","linter":"FinalNewline"}],"UI/Dist/Styleguide/Assets/SASS/Components/_ColourPalette.scss":[{"line":5,"column":1,"length":1,"severity":"warning","reason":"Avoid qualifying class selectors with an element.","linter":"QualifyingElement"},{"line":6,"column":1,"length":1,"severity":"warning","reason":"Line should be indented with spaces, not tabs","linter":"Indentation"},{"line":7,"column":1,"length":1,"severity":"warning","reason":"Line should be indented with spaces, not tabs","linter":"Indentation"},{"line":7,"column":2,"length":38,"severity":"warning","reason":"Properties should be ordered list-style, margin, padding","linter":"PropertySortOrder"},{"line":7,"column":2,"length":38,"severity":"warning","reason":"Colon after property should be followed by one space","linter":"SpaceAfterPropertyColon"},{"line":8,"column":1,"length":1,"severity":"warning","reason":"Line should be indented with spaces, not tabs","linter":"Indentation"},{"line":8,"column":2,"length":23,"severity":"warning","reason":"Colon after property should be followed by one space","linter":"SpaceAfterPropertyColon"},{"line":9,"column":1,"length":1,"severity":"warning","reason":"Line should be indented with spaces, not tabs","linter":"Indentation"},{"line":9,"column":2,"length":18,"severity":"warning","reason":"Colon after property should be followed by one space","linter":"SpaceAfterPropertyColon"},{"line":10,"column":1,"length":1,"severity":"warning","reason":"Rule declaration should be preceded by an empty line","linter":"EmptyLineBetweenBlocks"},{"line":10,"column":1,"length":1,"severity":"warning","reason":"Line should be indented with spaces, not tabs","linter":"Indentation"},{"line":12,"column":3,"length":20,"severity":"warning","reason":"Colon after property should be followed by one space","linter":"SpaceAfterPropertyColon"},{"line":13,"column":1,"length":1,"severity":"warning","reason":"Expected item on line 13 to appear before line 12. Rule sets should be ordered as follows: `@extends`, `@includes` without `@content`, properties, `@includes` with `@content`, nested rule sets","linter":"DeclarationOrder"},{"line":14,"column":9,"length":46,"severity":"warning","reason":"Colon after property should be followed by one space","linter":"SpaceAfterPropertyColon"},{"line":15,"column":3,"length":25,"severity":"warning","reason":"Colon after property should be followed by one space","linter":"SpaceAfterPropertyColon"},{"line":16,"column":1,"length":1,"severity":"warning","reason":"Rule declaration should be preceded by an empty line","linter":"EmptyLineBetweenBlocks"},{"line":17,"column":4,"length":53,"severity":"warning","reason":"Colon after property should be followed by one space","linter":"SpaceAfterPropertyColon"},{"line":18,"column":4,"length":15,"severity":"warning","reason":"Colon after property should be followed by one space","linter":"SpaceAfterPropertyColon"},{"line":19,"column":13,"length":47,"severity":"warning","reason":"Colon after property should be followed by one space","linter":"SpaceAfterPropertyColon"},{"line":20,"column":4,"length":14,"severity":"warning","reason":"Colon after property should be followed by one space","linter":"SpaceAfterPropertyColon"},{"line":21,"column":13,"length":49,"severity":"warning","reason":"Colon after property should be followed by one space","linter":"SpaceAfterPropertyColon"},{"line":22,"column":4,"length":15,"severity":"warning","reason":"Colon after property should be followed by one space","linter":"SpaceAfterPropertyColon"},{"line":23,"column":4,"length":33,"severity":"warning","reason":"Colon after property should be followed by one space","linter":"SpaceAfterPropertyColon"},{"line":24,"column":4,"length":24,"severity":"warning","reason":"Colon after property should be followed by one space","linter":"SpaceAfterPropertyColon"},{"line":25,"column":4,"length":15,"severity":"warning","reason":"Colon after property should be followed by one space","linter":"SpaceAfterPropertyColon"},{"line":28,"column":1,"length":1,"severity":"warning","reason":"Files should end with a trailing newline","linter":"FinalNewline"}],"UI/Dist/Styleguide/Assets/SASS/Components/_Icons.scss":[{"line":5,"column":1,"length":1,"severity":"warning","reason":"Avoid qualifying class selectors with an element.","linter":"QualifyingElement"},{"line":6,"column":1,"length":1,"severity":"warning","reason":"Line should be indented with spaces, not tabs","linter":"Indentation"},{"line":7,"column":1,"length":1,"severity":"warning","reason":"Line should be indented with spaces, not tabs","linter":"Indentation"},{"line":7,"column":2,"length":38,"severity":"warning","reason":"Properties should be ordered list-style, margin, padding","linter":"PropertySortOrder"},{"line":7,"column":2,"length":38,"severity":"warning","reason":"Colon after property should be followed by one space","linter":"SpaceAfterPropertyColon"},{"line":8,"column":1,"length":1,"severity":"warning","reason":"Line should be indented with spaces, not tabs","linter":"Indentation"},{"line":8,"column":2,"length":23,"severity":"warning","reason":"Colon after property should be followed by one space","linter":"SpaceAfterPropertyColon"},{"line":9,"column":1,"length":1,"severity":"warning","reason":"Line should be indented with spaces, not tabs","linter":"Indentation"},{"line":9,"column":2,"length":18,"severity":"warning","reason":"Colon after property should be followed by one space","linter":"SpaceAfterPropertyColon"},{"line":10,"column":1,"length":1,"severity":"warning","reason":"Line should be indented with spaces, not tabs","linter":"Indentation"},{"line":10,"column":1,"length":1,"severity":"warning","reason":"Rule declaration should be preceded by an empty line","linter":"EmptyLineBetweenBlocks"},{"line":11,"column":9,"length":78,"severity":"warning","reason":"Colon after property should be followed by one space","linter":"SpaceAfterPropertyColon"},{"line":12,"column":1,"length":1,"severity":"warning","reason":"Expected item on line 12 to appear before line 11. Rule sets should be ordered as follows: `@extends`, `@includes` without `@content`, properties, `@includes` with `@content`, nested rule sets","linter":"DeclarationOrder"},{"line":13,"column":3,"length":19,"severity":"warning","reason":"Colon after property should be followed by one space","linter":"SpaceAfterPropertyColon"},{"line":15,"column":9,"length":46,"severity":"warning","reason":"Colon after property should be followed by one space","linter":"SpaceAfterPropertyColon"},{"line":16,"column":9,"length":42,"severity":"warning","reason":"Properties should be ordered border, height, margin-bottom, position, text-align","linter":"PropertySortOrder"},{"line":16,"column":9,"length":42,"severity":"warning","reason":"Colon after property should be followed by one space","linter":"SpaceAfterPropertyColon"},{"line":17,"column":3,"length":25,"severity":"warning","reason":"Colon after property should be followed by one space","linter":"SpaceAfterPropertyColon"},{"line":18,"column":1,"length":1,"severity":"warning","reason":"Rule declaration should be preceded by an empty line","linter":"EmptyLineBetweenBlocks"},{"line":18,"column":1,"length":1,"severity":"warning","reason":"Each selector in a comma sequence should be on its own line","linter":"SingleLinePerSelector"},{"line":19,"column":13,"length":36,"severity":"warning","reason":"Colon after property should be followed by one space","linter":"SpaceAfterPropertyColon"},{"line":20,"column":13,"length":40,"severity":"warning","reason":"Colon after property should be followed by one space","linter":"SpaceAfterPropertyColon"},{"line":21,"column":13,"length":36,"severity":"warning","reason":"Colon after property should be followed by one space","linter":"SpaceAfterPropertyColon"},{"line":22,"column":1,"length":1,"severity":"warning","reason":"Rule declaration should be followed by an empty line","linter":"EmptyLineBetweenBlocks"},{"line":24,"column":4,"length":15,"severity":"warning","reason":"Colon after property should be followed by one space","linter":"SpaceAfterPropertyColon"},{"line":25,"column":13,"length":35,"severity":"warning","reason":"Colon after property should be followed by one space","linter":"SpaceAfterPropertyColon"},{"line":26,"column":4,"length":14,"severity":"warning","reason":"Colon after property should be followed by one space","linter":"SpaceAfterPropertyColon"},{"line":27,"column":13,"length":49,"severity":"warning","reason":"Colon after property should be followed by one space","linter":"SpaceAfterPropertyColon"},{"line":28,"column":4,"length":15,"severity":"warning","reason":"Colon after property should be followed by one space","linter":"SpaceAfterPropertyColon"},{"line":29,"column":4,"length":24,"severity":"warning","reason":"Colon after property should be followed by one space","linter":"SpaceAfterPropertyColon"},{"line":30,"column":4,"length":15,"severity":"warning","reason":"Colon after property should be followed by one space","linter":"SpaceAfterPropertyColon"},{"line":33,"column":1,"length":1,"severity":"warning","reason":"Files should end with a trailing newline","linter":"FinalNewline"}],"UI/Dist/Styleguide/Assets/SASS/Components/_Module.scss":[{"line":6,"column":1,"length":1,"severity":"warning","reason":"Line should be indented with spaces, not tabs","linter":"Indentation"},{"line":6,"column":2,"length":35,"severity":"warning","reason":"Colon after property should be followed by one space","linter":"SpaceAfterPropertyColon"},{"line":7,"column":1,"length":1,"severity":"warning","reason":"Line should be indented with spaces, not tabs","linter":"Indentation"},{"line":7,"column":1,"length":1,"severity":"warning","reason":"Expected item on line 7 to appear before line 6. Rule sets should be ordered as follows: `@extends`, `@includes` without `@content`, properties, `@includes` with `@content`, nested rule sets","linter":"DeclarationOrder"},{"line":8,"column":1,"length":1,"severity":"warning","reason":"Line should be indented with spaces, not tabs","linter":"Indentation"},{"line":8,"column":2,"length":41,"severity":"warning","reason":"Colon after property should be followed by one space","linter":"SpaceAfterPropertyColon"},{"line":9,"column":1,"length":1,"severity":"warning","reason":"Line should be indented with spaces, not tabs","linter":"Indentation"},{"line":9,"column":2,"length":25,"severity":"warning","reason":"Colon after property should be followed by one space","linter":"SpaceAfterPropertyColon"},{"line":10,"column":1,"length":1,"severity":"warning","reason":"Rule declaration should be preceded by an empty line","linter":"EmptyLineBetweenBlocks"},{"line":10,"column":1,"length":1,"severity":"warning","reason":"Line should be indented with spaces, not tabs","linter":"Indentation"},{"line":11,"column":3,"length":22,"severity":"warning","reason":"Colon after property should be followed by one space","linter":"SpaceAfterPropertyColon"},{"line":12,"column":3,"length":25,"severity":"warning","reason":"Colon after property should be followed by one space","linter":"SpaceAfterPropertyColon"},{"line":13,"column":9,"length":37,"severity":"warning","reason":"Colon after property should be followed by one space","linter":"SpaceAfterPropertyColon"},{"line":14,"column":3,"length":22,"severity":"warning","reason":"Colon after property should be followed by one space","linter":"SpaceAfterPropertyColon"},{"line":15,"column":3,"length":25,"severity":"warning","reason":"Colon after property should be followed by one space","linter":"SpaceAfterPropertyColon"},{"line":16,"column":1,"length":1,"severity":"warning","reason":"Rule declaration should be followed by an empty line","linter":"EmptyLineBetweenBlocks"},{"line":17,"column":1,"length":1,"severity":"warning","reason":"Line should be indented with spaces, not tabs","linter":"Indentation"},{"line":19,"column":6,"length":43,"severity":"warning","reason":"Colon after property should be followed by one space","linter":"SpaceAfterPropertyColon"},{"line":20,"column":3,"length":36,"severity":"warning","reason":"Colon after property should be followed by one space","linter":"SpaceAfterPropertyColon"},{"line":21,"column":1,"length":1,"severity":"warning","reason":"Rule declaration should be preceded by an empty line","linter":"EmptyLineBetweenBlocks"},{"line":22,"column":4,"length":21,"severity":"warning","reason":"Colon after property should be followed by one space","linter":"SpaceAfterPropertyColon"},{"line":24,"column":1,"length":1,"severity":"warning","reason":"Rule declaration should be followed by an empty line","linter":"EmptyLineBetweenBlocks"},{"line":25,"column":1,"length":1,"severity":"warning","reason":"Line should be indented with spaces, not tabs","linter":"Indentation"},{"line":26,"column":3,"length":20,"severity":"warning","reason":"Colon after property should be followed by one space","linter":"SpaceAfterPropertyColon"},{"line":28,"column":1,"length":1,"severity":"warning","reason":"Files should end with a trailing newline","linter":"FinalNewline"}],"UI/Dist/Styleguide/Assets/SASS/Components/_PrimaryNav.scss":[{"line":6,"column":1,"length":1,"severity":"warning","reason":"Line should be indented with spaces, not tabs","linter":"Indentation"},{"line":7,"column":1,"length":1,"severity":"warning","reason":"Line should be indented with spaces, not tabs","linter":"Indentation"},{"line":7,"column":1,"length":1,"severity":"warning","reason":"Rule declaration should be preceded by an empty line","linter":"EmptyLineBetweenBlocks"},{"line":8,"column":3,"length":22,"severity":"warning","reason":"Colon after property should be followed by one space","linter":"SpaceAfterPropertyColon"},{"line":9,"column":3,"length":16,"severity":"warning","reason":"Colon after property should be followed by one space","linter":"SpaceAfterPropertyColon"},{"line":10,"column":1,"length":1,"severity":"warning","reason":"Rule declaration should be preceded by an empty line","linter":"EmptyLineBetweenBlocks"},{"line":11,"column":4,"length":18,"severity":"warning","reason":"Colon after property should be followed by one space","linter":"SpaceAfterPropertyColon"},{"line":12,"column":4,"length":36,"severity":"warning","reason":"Colon after property should be followed by one space","linter":"SpaceAfterPropertyColon"},{"line":13,"column":1,"length":1,"severity":"warning","reason":"Rule declaration should be preceded by an empty line","linter":"EmptyLineBetweenBlocks"},{"line":13,"column":1,"length":1,"severity":"warning","reason":"Selector should have depth of applicability no greater than 3, but was 4","linter":"SelectorDepth"},{"line":13,"column":4,"length":2,"severity":"warning","reason":"Nesting should be no greater than 3, but was 4","linter":"NestingDepth"},{"line":15,"column":5,"length":28,"severity":"warning","reason":"Colon after property should be followed by one space","linter":"SpaceAfterPropertyColon"},{"line":16,"column":5,"length":26,"severity":"warning","reason":"Colon after property should be followed by one space","linter":"SpaceAfterPropertyColon"},{"line":17,"column":5,"length":20,"severity":"warning","reason":"Colon after property should be followed by one space","linter":"SpaceAfterPropertyColon"},{"line":18,"column":5,"length":21,"severity":"warning","reason":"Colon after property should be followed by one space","linter":"SpaceAfterPropertyColon"},{"line":19,"column":5,"length":17,"severity":"warning","reason":"Colon after property should be followed by one space","linter":"SpaceAfterPropertyColon"},{"line":20,"column":5,"length":24,"severity":"warning","reason":"Colon after property should be followed by one space","linter":"SpaceAfterPropertyColon"},{"line":21,"column":5,"length":28,"severity":"warning","reason":"Colon after property should be followed by one space","linter":"SpaceAfterPropertyColon"},{"line":22,"column":1,"length":1,"severity":"warning","reason":"Expected item on line 22 to appear before line 15. Rule sets should be ordered as follows: `@extends`, `@includes` without `@content`, properties, `@includes` with `@content`, nested rule sets","linter":"DeclarationOrder"},{"line":23,"column":1,"length":1,"severity":"warning","reason":"Selector should have depth of applicability no greater than 3, but was 4","linter":"SelectorDepth"},{"line":25,"column":6,"length":42,"severity":"warning","reason":"Colon after property should be followed by one space","linter":"SpaceAfterPropertyColon"},{"line":30,"column":1,"length":1,"severity":"warning","reason":"Files should end with a trailing newline","linter":"FinalNewline"}],"UI/Dist/Styleguide/Assets/SASS/Components/_SecondaryNav.scss":[{"line":6,"column":1,"length":1,"severity":"warning","reason":"Line should be indented with spaces, not tabs","linter":"Indentation"},{"line":7,"column":1,"length":1,"severity":"warning","reason":"Line should be indented with spaces, not tabs","linter":"Indentation"},{"line":7,"column":2,"length":35,"severity":"warning","reason":"Colon after property should be followed by one space","linter":"SpaceAfterPropertyColon"},{"line":8,"column":1,"length":1,"severity":"warning","reason":"Expected item on line 8 to appear before line 7. Rule sets should be ordered as follows: `@extends`, `@includes` without `@content`, properties, `@includes` with `@content`, nested rule sets","linter":"DeclarationOrder"},{"line":8,"column":1,"length":1,"severity":"warning","reason":"Line should be indented with spaces, not tabs","linter":"Indentation"},{"line":9,"column":1,"length":1,"severity":"warning","reason":"Line should be indented with spaces, not tabs","linter":"Indentation"},{"line":10,"column":3,"length":22,"severity":"warning","reason":"Colon after property should be followed by one space","linter":"SpaceAfterPropertyColon"},{"line":11,"column":3,"length":16,"severity":"warning","reason":"Colon after property should be followed by one space","linter":"SpaceAfterPropertyColon"},{"line":12,"column":1,"length":1,"severity":"warning","reason":"Rule declaration should be preceded by an empty line","linter":"EmptyLineBetweenBlocks"},{"line":13,"column":1,"length":1,"severity":"warning","reason":"Selector should have depth of applicability no greater than 3, but was 4","linter":"SelectorDepth"},{"line":13,"column":4,"length":2,"severity":"warning","reason":"Nesting should be no greater than 3, but was 4","linter":"NestingDepth"},{"line":14,"column":5,"length":57,"severity":"warning","reason":"Colon after property should be followed by one space","linter":"SpaceAfterPropertyColon"},{"line":15,"column":5,"length":33,"severity":"warning","reason":"Colon after property should be followed by one space","linter":"SpaceAfterPropertyColon"},{"line":16,"column":5,"length":19,"severity":"warning","reason":"Colon after property should be followed by one space","linter":"SpaceAfterPropertyColon"},{"line":17,"column":5,"length":52,"severity":"warning","reason":"Colon after property should be followed by one space","linter":"SpaceAfterPropertyColon"},{"line":18,"column":5,"length":23,"severity":"warning","reason":"Colon after property should be followed by one space","linter":"SpaceAfterPropertyColon"},{"line":19,"column":5,"length":24,"severity":"warning","reason":"Colon after property should be followed by one space","linter":"SpaceAfterPropertyColon"},{"line":20,"column":1,"length":1,"severity":"warning","reason":"Expected item on line 20 to appear before line 14. Rule sets should be ordered as follows: `@extends`, `@includes` without `@content`, properties, `@includes` with `@content`, nested rule sets","linter":"DeclarationOrder"},{"line":21,"column":1,"length":1,"severity":"warning","reason":"Selector should have depth of applicability no greater than 3, but was 4","linter":"SelectorDepth"},{"line":22,"column":6,"length":55,"severity":"warning","reason":"Colon after property should be followed by one space","linter":"SpaceAfterPropertyColon"},{"line":23,"column":6,"length":14,"severity":"warning","reason":"Colon after property should be followed by one space","linter":"SpaceAfterPropertyColon"},{"line":24,"column":6,"length":16,"severity":"warning","reason":"Colon after property should be followed by one space","linter":"SpaceAfterPropertyColon"},{"line":25,"column":6,"length":19,"severity":"warning","reason":"Colon after property should be followed by one space","linter":"SpaceAfterPropertyColon"},{"line":26,"column":6,"length":22,"severity":"warning","reason":"Colon after property should be followed by one space","linter":"SpaceAfterPropertyColon"},{"line":27,"column":6,"length":29,"severity":"warning","reason":"Colon after property should be followed by one space","linter":"SpaceAfterPropertyColon"},{"line":28,"column":6,"length":12,"severity":"warning","reason":"Colon after property should be followed by one space","linter":"SpaceAfterPropertyColon"},{"line":29,"column":6,"length":14,"severity":"warning","reason":"Colon after property should be followed by one space","linter":"SpaceAfterPropertyColon"},{"line":30,"column":1,"length":1,"severity":"warning","reason":"Rule declaration should be followed by an empty line","linter":"EmptyLineBetweenBlocks"},{"line":31,"column":1,"length":1,"severity":"warning","reason":"Selector should have depth of applicability no greater than 3, but was 4","linter":"SelectorDepth"},{"line":32,"column":6,"length":51,"severity":"warning","reason":"Colon after property should be followed by one space","linter":"SpaceAfterPropertyColon"},{"line":34,"column":1,"length":1,"severity":"warning","reason":"Rule declaration should be followed by an empty line","linter":"EmptyLineBetweenBlocks"},{"line":35,"column":1,"length":1,"severity":"warning","reason":"Selector should have depth of applicability no greater than 3, but was 4","linter":"SelectorDepth"},{"line":35,"column":4,"length":16,"severity":"warning","reason":"Nesting should be no greater than 3, but was 4","linter":"NestingDepth"},{"line":37,"column":1,"length":1,"severity":"warning","reason":"Rule declaration should be followed by an empty line","linter":"EmptyLineBetweenBlocks"},{"line":38,"column":1,"length":1,"severity":"warning","reason":"Selector should have depth of applicability no greater than 3, but was 4","linter":"SelectorDepth"},{"line":38,"column":4,"length":15,"severity":"warning","reason":"Nesting should be no greater than 3, but was 4","linter":"NestingDepth"},{"line":40,"column":1,"length":1,"severity":"warning","reason":"Rule declaration should be followed by an empty line","linter":"EmptyLineBetweenBlocks"},{"line":41,"column":1,"length":1,"severity":"warning","reason":"Selector should have depth of applicability no greater than 3, but was 4","linter":"SelectorDepth"},{"line":41,"column":4,"length":15,"severity":"warning","reason":"Nesting should be no greater than 3, but was 4","linter":"NestingDepth"},{"line":46,"column":1,"length":1,"severity":"warning","reason":"Files should end with a trailing newline","linter":"FinalNewline"}],"UI/Dist/Styleguide/Assets/SASS/Components/_StyleguideParagraph.scss":[{"line":6,"column":1,"length":1,"severity":"warning","reason":"Avoid qualifying class selectors with an element.","linter":"QualifyingElement"},{"line":7,"column":1,"length":1,"severity":"warning","reason":"Line should be indented with spaces, not tabs","linter":"Indentation"},{"line":7,"column":2,"length":20,"severity":"warning","reason":"Colon after property should be followed by one space","linter":"SpaceAfterPropertyColon"},{"line":8,"column":1,"length":1,"severity":"warning","reason":"Files should end with a trailing newline","linter":"FinalNewline"}],"UI/Dist/Styleguide/Assets/SASS/Regions/_Footer.scss":[{"line":6,"column":1,"length":1,"severity":"warning","reason":"Line should be indented with spaces, not tabs","linter":"Indentation"},{"line":6,"column":2,"length":35,"severity":"warning","reason":"Colon after property should be followed by one space","linter":"SpaceAfterPropertyColon"},{"line":7,"column":1,"length":1,"severity":"warning","reason":"Line should be indented with spaces, not tabs","linter":"Indentation"},{"line":7,"column":2,"length":28,"severity":"warning","reason":"Colon after property should be followed by one space","linter":"SpaceAfterPropertyColon"},{"line":8,"column":1,"length":1,"severity":"warning","reason":"Files should end with a trailing newline","linter":"FinalNewline"}],"UI/Dist/Styleguide/Assets/SASS/Regions/_Header.scss":[{"line":6,"column":1,"length":1,"severity":"warning","reason":"Line should be indented with spaces, not tabs","linter":"Indentation"},{"line":7,"column":1,"length":1,"severity":"warning","reason":"Line should be indented with spaces, not tabs","linter":"Indentation"},{"line":7,"column":2,"length":40,"severity":"warning","reason":"Colon after property should be followed by one space","linter":"SpaceAfterPropertyColon"},{"line":8,"column":1,"length":1,"severity":"warning","reason":"Line should be indented with spaces, not tabs","linter":"Indentation"},{"line":8,"column":2,"length":37,"severity":"warning","reason":"Properties should be ordered background, margin-bottom, padding","linter":"PropertySortOrder"},{"line":8,"column":2,"length":37,"severity":"warning","reason":"Colon after property should be followed by one space","linter":"SpaceAfterPropertyColon"},{"line":9,"column":1,"length":1,"severity":"warning","reason":"Line should be indented with spaces, not tabs","linter":"Indentation"},{"line":9,"column":2,"length":41,"severity":"warning","reason":"Colon after property should be followed by one space","linter":"SpaceAfterPropertyColon"},{"line":10,"column":1,"length":1,"severity":"warning","reason":"Rule declaration should be preceded by an empty line","linter":"EmptyLineBetweenBlocks"},{"line":10,"column":1,"length":1,"severity":"warning","reason":"Line should be indented with spaces, not tabs","linter":"Indentation"},{"line":11,"column":3,"length":18,"severity":"warning","reason":"Colon after property should be followed by one space","linter":"SpaceAfterPropertyColon"},{"line":12,"column":3,"length":25,"severity":"warning","reason":"Colon after property should be followed by one space","linter":"SpaceAfterPropertyColon"},{"line":12,"column":3,"length":25,"severity":"warning","reason":"Properties should be ordered float, font-size, line-height, margin","linter":"PropertySortOrder"},{"line":13,"column":3,"length":40,"severity":"warning","reason":"Colon after property should be followed by one space","linter":"SpaceAfterPropertyColon"},{"line":14,"column":3,"length":19,"severity":"warning","reason":"Colon after property should be followed by one space","linter":"SpaceAfterPropertyColon"},{"line":15,"column":1,"length":1,"severity":"warning","reason":"Rule declaration should be followed by an empty line","linter":"EmptyLineBetweenBlocks"},{"line":16,"column":1,"length":1,"severity":"warning","reason":"Line should be indented with spaces, not tabs","linter":"Indentation"},{"line":17,"column":3,"length":18,"severity":"warning","reason":"Colon after property should be followed by one space","linter":"SpaceAfterPropertyColon"},{"line":18,"column":3,"length":21,"severity":"warning","reason":"Colon after property should be followed by one space","linter":"SpaceAfterPropertyColon"},{"line":20,"column":1,"length":1,"severity":"warning","reason":"Files should end with a trailing newline","linter":"FinalNewline"}],"UI/Dist/Styleguide/Assets/SASS/Regions/_Layout.scss":[{"line":6,"column":1,"length":1,"severity":"warning","reason":"Line should be indented 2 spaces, but was indented 4 spaces","linter":"Indentation"},{"line":10,"column":1,"length":1,"severity":"warning","reason":"Line should be indented 2 spaces, but was indented 4 spaces","linter":"Indentation"},{"line":11,"column":1,"length":1,"severity":"warning","reason":"Files should end with a trailing newline","linter":"FinalNewline"}],"UI/Dist/Styleguide/Assets/SASS/Shared/_Clearfix.scss":[{"line":6,"column":1,"length":1,"severity":"warning","reason":"Line should be indented with spaces, not tabs","linter":"Indentation"},{"line":7,"column":3,"length":19,"severity":"warning","reason":"Colon after property should be followed by one space","linter":"SpaceAfterPropertyColon"},{"line":8,"column":3,"length":17,"severity":"warning","reason":"Colon after property should be followed by one space","linter":"SpaceAfterPropertyColon"},{"line":9,"column":3,"length":21,"severity":"warning","reason":"Colon after property should be followed by one space","linter":"SpaceAfterPropertyColon"},{"line":11,"column":1,"length":1,"severity":"warning","reason":"Files should end with a trailing newline","linter":"FinalNewline"}],"UI/Dist/Styleguide/Assets/SASS/Shared/_ColourPalette.scss":[{"line":18,"column":1,"length":1,"severity":"warning","reason":"Files should end with a trailing newline","linter":"FinalNewline"}],"UI/Dist/Styleguide/Assets/SASS/Shared/_Grid.scss":[{"line":15,"column":1,"length":1,"severity":"warning","reason":"Line should be indented 2 spaces, but was indented 4 spaces","linter":"Indentation"},{"line":16,"column":1,"length":1,"severity":"warning","reason":"Line should be indented 2 spaces, but was indented 4 spaces","linter":"Indentation"},{"line":16,"column":5,"length":25,"severity":"warning","reason":"Colon after property should be followed by one space","linter":"SpaceAfterPropertyColon"},{"line":17,"column":1,"length":1,"severity":"warning","reason":"Files should end with a trailing newline","linter":"FinalNewline"}],"UI/Dist/Styleguide/Assets/SASS/Shared/_MIPalette.scss":[{"line":2,"column":1,"length":1,"severity":"warning","reason":"Line should be indented 2 spaces, but was indented 4 spaces","linter":"Indentation"},{"line":3,"column":1,"length":1,"severity":"warning","reason":"Files should end with a trailing newline","linter":"FinalNewline"}],"UI/Dist/Styleguide/Assets/SASS/Shared/_Settings.scss":[{"line":1,"column":1,"length":1,"severity":"warning","reason":"Use `//` comments everywhere","linter":"Comment"},{"line":19,"column":1,"length":1,"severity":"warning","reason":"Declaration should be terminated by a single semicolon","linter":"TrailingSemicolon"},{"line":24,"column":1,"length":1,"severity":"warning","reason":"Files should end with a trailing newline","linter":"FinalNewline"}],"UI/Dist/Styleguide/Assets/SASS/Styleguide.scss":[{"line":1,"column":9,"length":9,"severity":"warning","reason":"Prefer single quoted strings","linter":"StringQuotes"},{"line":2,"column":9,"length":6,"severity":"warning","reason":"Prefer single quoted strings","linter":"StringQuotes"},{"line":5,"column":9,"length":17,"severity":"warning","reason":"Prefer single quoted strings","linter":"StringQuotes"},{"line":6,"column":9,"length":13,"severity":"warning","reason":"Prefer single quoted strings","linter":"StringQuotes"},{"line":7,"column":9,"length":22,"severity":"warning","reason":"Prefer single quoted strings","linter":"StringQuotes"},{"line":10,"column":9,"length":17,"severity":"warning","reason":"Prefer single quoted strings","linter":"StringQuotes"},{"line":11,"column":9,"length":18,"severity":"warning","reason":"Prefer single quoted strings","linter":"StringQuotes"},{"line":14,"column":9,"length":11,"severity":"warning","reason":"Prefer single quoted strings","linter":"StringQuotes"},{"line":15,"column":9,"length":17,"severity":"warning","reason":"Prefer single quoted strings","linter":"StringQuotes"},{"line":16,"column":9,"length":12,"severity":"warning","reason":"Prefer single quoted strings","linter":"StringQuotes"},{"line":19,"column":9,"length":32,"severity":"warning","reason":"Prefer single quoted strings","linter":"StringQuotes"},{"line":20,"column":9,"length":23,"severity":"warning","reason":"Prefer single quoted strings","linter":"StringQuotes"},{"line":21,"column":9,"length":25,"severity":"warning","reason":"Prefer single quoted strings","linter":"StringQuotes"},{"line":22,"column":9,"length":19,"severity":"warning","reason":"Prefer single quoted strings","linter":"StringQuotes"},{"line":23,"column":9,"length":24,"severity":"warning","reason":"Prefer single quoted strings","linter":"StringQuotes"},{"line":24,"column":9,"length":26,"severity":"warning","reason":"Prefer single quoted strings","linter":"StringQuotes"},{"line":25,"column":9,"length":18,"severity":"warning","reason":"Prefer single quoted strings","linter":"StringQuotes"},{"line":28,"column":9,"length":16,"severity":"warning","reason":"Prefer single quoted strings","linter":"StringQuotes"},{"line":29,"column":9,"length":16,"severity":"warning","reason":"Prefer single quoted strings","linter":"StringQuotes"},{"line":30,"column":9,"length":16,"severity":"warning","reason":"Prefer single quoted strings","linter":"StringQuotes"},{"line":33,"column":1,"length":1,"severity":"warning","reason":"Files should end with a trailing newline","linter":"FinalNewline"},{"line":33,"column":9,"length":24,"severity":"warning","reason":"Prefer single quoted strings","linter":"StringQuotes"}],"UI/Dist/Styleguide/Assets/SASS/Vendor/_monokai_sublime.scss":[{"line":1,"column":1,"length":1,"severity":"warning","reason":"Use `//` comments everywhere","linter":"Comment"},{"line":8,"column":3,"length":14,"severity":"warning","reason":"Properties should be ordered background, display, overflow-x, padding, -webkit-text-size-adjust","linter":"PropertySortOrder"},{"line":12,"column":3,"length":30,"severity":"warning","reason":"Avoid vendor prefixes.","linter":"VendorPrefix"},{"line":23,"column":10,"length":7,"severity":"warning","reason":"Color literals like `#f8f8f2` should only be used in variable declarations; they should be referred to via variable everywhere else.","linter":"ColorVariable"},{"line":29,"column":10,"length":7,"severity":"warning","reason":"Color literals like `#a8a8a2` should only be used in variable declarations; they should be referred to via variable everywhere else.","linter":"ColorVariable"},{"line":32,"column":1,"length":1,"severity":"warning","reason":"Selector `hljs-horizontal_rule` should be written in lowercase with hyphens","linter":"SelectorFormat"},{"line":40,"column":10,"length":7,"severity":"warning","reason":"Color literals like `#ae81ff` should only be used in variable declarations; they should be referred to via variable everywhere else.","linter":"ColorVariable"},{"line":48,"column":10,"length":7,"severity":"warning","reason":"Color literals like `#a6e22e` should only be used in variable declarations; they should be referred to via variable everywhere else.","linter":"ColorVariable"},{"line":51,"column":1,"length":1,"severity":"warning","reason":"Selector `hljs-link_url` should be written in lowercase with hyphens","linter":"SelectorFormat"},{"line":86,"column":10,"length":7,"severity":"warning","reason":"Color literals like `#f92672` should only be used in variable declarations; they should be referred to via variable everywhere else.","linter":"ColorVariable"},{"line":95,"column":10,"length":7,"severity":"warning","reason":"Color literals like `#66d9ef` should only be used in variable declarations; they should be referred to via variable everywhere else.","linter":"ColorVariable"},{"line":102,"column":10,"length":7,"severity":"warning","reason":"Color literals like `#f8f8f2` should only be used in variable declarations; they should be referred to via variable everywhere else.","linter":"ColorVariable"},{"line":105,"column":1,"length":1,"severity":"warning","reason":"Selector `hljs-built_in` should be written in lowercase with hyphens","linter":"SelectorFormat"},{"line":105,"column":1,"length":1,"severity":"warning","reason":"Selector `hljs-link_label` should be written in lowercase with hyphens","linter":"SelectorFormat"},{"line":105,"column":1,"length":1,"severity":"warning","reason":"Selector `hljs-link_url` should be written in lowercase with hyphens","linter":"SelectorFormat"},{"line":105,"column":1,"length":1,"severity":"warning","reason":"Selector `hljs-attr_selector` should be written in lowercase with hyphens","linter":"SelectorFormat"},{"line":105,"column":1,"length":1,"severity":"warning","reason":"Selector `hljs-template_tag` should be written in lowercase with hyphens","linter":"SelectorFormat"},{"line":128,"column":10,"length":7,"severity":"warning","reason":"Color literals like `#e6db74` should only be used in variable declarations; they should be referred to via variable everywhere else.","linter":"ColorVariable"},{"line":141,"column":10,"length":7,"severity":"warning","reason":"Color literals like `#75715e` should only be used in variable declarations; they should be referred to via variable everywhere else.","linter":"ColorVariable"},{"line":153,"column":12,"length":3,"severity":"warning","reason":"`0.5` should be written without a leading zero as `.5`","linter":"LeadingZero"}],"UI/SRC/Sass/Base/_Links.scss":[{"line":6,"column":1,"length":1,"severity":"warning","reason":"Line should be indented with spaces, not tabs","linter":"Indentation"},{"line":6,"column":2,"length":36,"severity":"warning","reason":"Colon after property should be followed by one space","linter":"SpaceAfterPropertyColon"},{"line":7,"column":1,"length":1,"severity":"warning","reason":"Files should end with a trailing newline","linter":"FinalNewline"}],"UI/SRC/Sass/Base/_Main.scss":[{"line":6,"column":1,"length":1,"severity":"warning","reason":"Line should be indented with spaces, not tabs","linter":"Indentation"},{"line":6,"column":2,"length":71,"severity":"warning","reason":"Colon after property should be followed by one space","linter":"SpaceAfterPropertyColon"},{"line":7,"column":1,"length":1,"severity":"warning","reason":"Files should end with a trailing newline","linter":"FinalNewline"}],"UI/SRC/Sass/Base/_Paragraphs.scss":[{"line":6,"column":1,"length":1,"severity":"warning","reason":"Line should be indented with spaces, not tabs","linter":"Indentation"},{"line":6,"column":2,"length":36,"severity":"warning","reason":"Colon after property should be followed by one space","linter":"SpaceAfterPropertyColon"},{"line":7,"column":1,"length":1,"severity":"warning","reason":"Files should end with a trailing newline","linter":"FinalNewline"}],"UI/SRC/Sass/Default.scss":[{"line":1,"column":9,"length":9,"severity":"warning","reason":"Prefer single quoted strings","linter":"StringQuotes"},{"line":2,"column":9,"length":6,"severity":"warning","reason":"Prefer single quoted strings","linter":"StringQuotes"},{"line":5,"column":9,"length":17,"severity":"warning","reason":"Prefer single quoted strings","linter":"StringQuotes"},{"line":6,"column":9,"length":13,"severity":"warning","reason":"Prefer single quoted strings","linter":"StringQuotes"},{"line":7,"column":9,"length":22,"severity":"warning","reason":"Prefer single quoted strings","linter":"StringQuotes"},{"line":10,"column":9,"length":14,"severity":"warning","reason":"Prefer single quoted strings","linter":"StringQuotes"},{"line":13,"column":9,"length":17,"severity":"warning","reason":"Prefer single quoted strings","linter":"StringQuotes"},{"line":14,"column":9,"length":18,"severity":"warning","reason":"Prefer single quoted strings","linter":"StringQuotes"},{"line":17,"column":9,"length":11,"severity":"warning","reason":"Prefer single quoted strings","linter":"StringQuotes"},{"line":18,"column":9,"length":12,"severity":"warning","reason":"Prefer single quoted strings","linter":"StringQuotes"},{"line":19,"column":9,"length":17,"severity":"warning","reason":"Prefer single quoted strings","linter":"StringQuotes"},{"line":21,"column":1,"length":1,"severity":"warning","reason":"Files should end with a trailing newline","linter":"FinalNewline"}],"UI/SRC/Sass/Shared/_Clearfix.scss":[{"line":1,"column":1,"length":1,"severity":"warning","reason":"Use `//` comments everywhere","linter":"Comment"},{"line":15,"column":1,"length":1,"severity":"warning","reason":"Line should be indented with spaces, not tabs","linter":"Indentation"},{"line":16,"column":3,"length":19,"severity":"warning","reason":"Colon after property should be followed by one space","linter":"SpaceAfterPropertyColon"},{"line":17,"column":3,"length":17,"severity":"warning","reason":"Colon after property should be followed by one space","linter":"SpaceAfterPropertyColon"},{"line":18,"column":3,"length":21,"severity":"warning","reason":"Colon after property should be followed by one space","linter":"SpaceAfterPropertyColon"},{"line":20,"column":1,"length":1,"severity":"warning","reason":"Files should end with a trailing newline","linter":"FinalNewline"}],"UI/SRC/Sass/Shared/_ColourPalette.scss":[{"line":1,"column":1,"length":1,"severity":"warning","reason":"Use `//` comments everywhere","linter":"Comment"},{"line":43,"column":1,"length":1,"severity":"warning","reason":"Files should end with a trailing newline","linter":"FinalNewline"}],"UI/SRC/Sass/Shared/_Grid.scss":[{"line":15,"column":1,"length":1,"severity":"warning","reason":"Line should be indented 2 spaces, but was indented 4 spaces","linter":"Indentation"},{"line":16,"column":1,"length":1,"severity":"warning","reason":"Files should end with a trailing newline","linter":"FinalNewline"}],"UI/SRC/Sass/Shared/_MIPalette.scss":[{"line":2,"column":1,"length":1,"severity":"warning","reason":"Line should be indented 2 spaces, but was indented 4 spaces","linter":"Indentation"},{"line":3,"column":1,"length":1,"severity":"warning","reason":"Files should end with a trailing newline","linter":"FinalNewline"}],"UI/SRC/Sass/Shared/_Reset.scss":[{"line":1,"column":1,"length":1,"severity":"warning","reason":"Use `//` comments everywhere","linter":"Comment"},{"line":11,"column":1,"length":1,"severity":"warning","reason":"Line should be indented with spaces, not tabs","linter":"Indentation"},{"line":18,"column":1,"length":1,"severity":"warning","reason":"Each selector in a comma sequence should be on its own line","linter":"SingleLinePerSelector"},{"line":20,"column":1,"length":1,"severity":"warning","reason":"Each selector in a comma sequence should be on its own line","linter":"SingleLinePerSelector"},{"line":21,"column":1,"length":1,"severity":"warning","reason":"Each selector in a comma sequence should be on its own line","linter":"SingleLinePerSelector"},{"line":22,"column":1,"length":1,"severity":"warning","reason":"Each selector in a comma sequence should be on its own line","linter":"SingleLinePerSelector"},{"line":23,"column":1,"length":1,"severity":"warning","reason":"Each selector in a comma sequence should be on its own line","linter":"SingleLinePerSelector"},{"line":24,"column":1,"length":1,"severity":"warning","reason":"Each selector in a comma sequence should be on its own line","linter":"SingleLinePerSelector"},{"line":25,"column":1,"length":1,"severity":"warning","reason":"Line should be indented with spaces, not tabs","linter":"Indentation"},{"line":25,"column":2,"length":18,"severity":"warning","reason":"Colon after property should be followed by one space","linter":"SpaceAfterPropertyColon"},{"line":26,"column":1,"length":1,"severity":"warning","reason":"Line should be indented with spaces, not tabs","linter":"Indentation"},{"line":26,"column":1,"length":1,"severity":"warning","reason":"Each selector in a comma sequence should be on its own line","linter":"SingleLinePerSelector"},{"line":26,"column":2,"length":20,"severity":"warning","reason":"Colon after property should be followed by one space","linter":"SpaceAfterPropertyColon"},{"line":27,"column":1,"length":1,"severity":"warning","reason":"Each selector in a comma sequence should be on its own line","linter":"SingleLinePerSelector"},{"line":29,"column":1,"length":1,"severity":"warning","reason":"Each selector in a comma sequence should be on its own line","linter":"SingleLinePerSelector"},{"line":29,"column":1,"length":1,"severity":"warning","reason":"Each selector in a comma sequence should be on its own line","linter":"SingleLinePerSelector"},{"line":30,"column":1,"length":1,"severity":"warning","reason":"Each selector in a comma sequence should be on its own line","linter":"SingleLinePerSelector"},{"line":30,"column":1,"length":1,"severity":"warning","reason":"Each selector in a comma sequence should be on its own line","linter":"SingleLinePerSelector"},{"line":31,"column":1,"length":1,"severity":"warning","reason":"Each selector in a comma sequence should be on its own line","linter":"SingleLinePerSelector"},{"line":32,"column":1,"length":1,"severity":"warning","reason":"Each selector in a comma sequence should be on its own line","linter":"SingleLinePerSelector"},{"line":33,"column":1,"length":1,"severity":"warning","reason":"Each selector in a comma sequence should be on its own line","linter":"SingleLinePerSelector"},{"line":33,"column":1,"length":1,"severity":"warning","reason":"Each selector in a comma sequence should be on its own line","linter":"SingleLinePerSelector"},{"line":33,"column":3,"length":26,"severity":"warning","reason":"Colon after property should be followed by one space","linter":"SpaceAfterPropertyColon"},{"line":34,"column":1,"length":1,"severity":"warning","reason":"Each selector in a comma sequence should be on its own line","linter":"SingleLinePerSelector"},{"line":35,"column":1,"length":1,"severity":"warning","reason":"Each selector in a comma sequence should be on its own line","linter":"SingleLinePerSelector"},{"line":36,"column":1,"length":1,"severity":"warning","reason":"Each selector in a comma sequence should be on its own line","linter":"SingleLinePerSelector"},{"line":36,"column":1,"length":1,"severity":"warning","reason":"Each selector in a comma sequence should be on its own line","linter":"SingleLinePerSelector"},{"line":36,"column":1,"length":1,"severity":"warning","reason":"Each selector in a comma sequence should be on its own line","linter":"SingleLinePerSelector"},{"line":37,"column":1,"length":1,"severity":"warning","reason":"Each selector in a comma sequence should be on its own line","linter":"SingleLinePerSelector"},{"line":37,"column":1,"length":1,"severity":"warning","reason":"Each selector in a comma sequence should be on its own line","linter":"SingleLinePerSelector"},{"line":38,"column":1,"length":1,"severity":"warning","reason":"Each selector in a comma sequence should be on its own line","linter":"SingleLinePerSelector"},{"line":38,"column":1,"length":1,"severity":"warning","reason":"Each selector in a comma sequence should be on its own line","linter":"SingleLinePerSelector"},{"line":38,"column":3,"length":33,"severity":"warning","reason":"Colon after property should be followed by one space","linter":"SpaceAfterPropertyColon"},{"line":39,"column":1,"length":1,"severity":"warning","reason":"Each selector in a comma sequence should be on its own line","linter":"SingleLinePerSelector"},{"line":39,"column":3,"length":32,"severity":"warning","reason":"Colon after property should be followed by one space","linter":"SpaceAfterPropertyColon"},{"line":40,"column":1,"length":1,"severity":"warning","reason":"Each selector in a comma sequence should be on its own line","linter":"SingleLinePerSelector"},{"line":40,"column":1,"length":1,"severity":"warning","reason":"Each selector in a comma sequence should be on its own line","linter":"SingleLinePerSelector"},{"line":41,"column":1,"length":1,"severity":"warning","reason":"Each selector in a comma sequence should be on its own line","linter":"SingleLinePerSelector"},{"line":44,"column":3,"length":34,"severity":"warning","reason":"Colon after property should be followed by one space","linter":"SpaceAfterPropertyColon"},{"line":48,"column":3,"length":25,"severity":"warning","reason":"Colon after property should be followed by one space","linter":"SpaceAfterPropertyColon"},{"line":49,"column":3,"length":21,"severity":"warning","reason":"Colon after property should be followed by one space","linter":"SpaceAfterPropertyColon"},{"line":53,"column":1,"length":1,"severity":"warning","reason":"Line should be indented with spaces, not tabs","linter":"Indentation"},{"line":53,"column":2,"length":32,"severity":"warning","reason":"Colon after property should be followed by one space","linter":"SpaceAfterPropertyColon"},{"line":54,"column":1,"length":1,"severity":"warning","reason":"Line should be indented with spaces, not tabs","linter":"Indentation"},{"line":54,"column":2,"length":24,"severity":"warning","reason":"Colon after property should be followed by one space","linter":"SpaceAfterPropertyColon"},{"line":57,"column":1,"length":1,"severity":"warning","reason":"Each selector in a comma sequence should be on its own line","linter":"SingleLinePerSelector"},{"line":58,"column":3,"length":22,"severity":"warning","reason":"Colon after property should be followed by one space","linter":"SpaceAfterPropertyColon"},{"line":61,"column":1,"length":1,"severity":"warning","reason":"Each selector in a comma sequence should be on its own line","linter":"SingleLinePerSelector"},{"line":65,"column":1,"length":1,"severity":"warning","reason":"Each selector in a comma sequence should be on its own line","linter":"SingleLinePerSelector"},{"line":66,"column":1,"length":1,"severity":"warning","reason":"Line should be indented with spaces, not tabs","linter":"Indentation"},{"line":66,"column":2,"length":27,"severity":"warning","reason":"Colon after property should be followed by one space","linter":"SpaceAfterPropertyColon"},{"line":70,"column":3,"length":34,"severity":"warning","reason":"Colon after property should be followed by one space","linter":"SpaceAfterPropertyColon"},{"line":75,"column":3,"length":23,"severity":"warning","reason":"Colon after property should be followed by one space","linter":"SpaceAfterPropertyColon"},{"line":76,"column":3,"length":23,"severity":"warning","reason":"Colon after property should be followed by one space","linter":"SpaceAfterPropertyColon"},{"line":77,"column":3,"length":27,"severity":"warning","reason":"Colon after property should be followed by one space","linter":"SpaceAfterPropertyColon"},{"line":78,"column":3,"length":32,"severity":"warning","reason":"Colon after property should be followed by one space","linter":"SpaceAfterPropertyColon"},{"line":82,"column":1,"length":1,"severity":"warning","reason":"Line should be indented with spaces, not tabs","linter":"Indentation"},{"line":82,"column":2,"length":24,"severity":"warning","reason":"Colon after property should be followed by one space","linter":"SpaceAfterPropertyColon"},{"line":82,"column":20,"length":6,"severity":"warning","reason":"`0.5` should be written without a leading zero as `.5`","linter":"LeadingZero"},{"line":86,"column":1,"length":1,"severity":"warning","reason":"Line should be indented with spaces, not tabs","linter":"Indentation"},{"line":86,"column":2,"length":24,"severity":"warning","reason":"Colon after property should be followed by one space","linter":"SpaceAfterPropertyColon"},{"line":86,"column":19,"length":7,"severity":"warning","reason":"`0.25` should be written without a leading zero as `.25`","linter":"LeadingZero"},{"line":89,"column":1,"length":1,"severity":"warning","reason":"Avoid qualifying attribute selectors with an element.","linter":"QualifyingElement"},{"line":89,"column":1,"length":1,"severity":"warning","reason":"Avoid qualifying attribute selectors with an element.","linter":"QualifyingElement"},{"line":91,"column":1,"length":1,"severity":"warning","reason":"Line should be indented with spaces, not tabs","linter":"Indentation"},{"line":91,"column":2,"length":21,"severity":"warning","reason":"Colon after property should be followed by one space","linter":"SpaceAfterPropertyColon"},{"line":95,"column":1,"length":1,"severity":"warning","reason":"Line should be indented with spaces, not tabs","linter":"Indentation"},{"line":95,"column":2,"length":31,"severity":"warning","reason":"Colon after property should be followed by one space","linter":"SpaceAfterPropertyColon"},{"line":99,"column":1,"length":1,"severity":"warning","reason":"Line should be indented with spaces, not tabs","linter":"Indentation"},{"line":99,"column":2,"length":26,"severity":"warning","reason":"Colon after property should be followed by one space","linter":"SpaceAfterPropertyColon"},{"line":102,"column":1,"length":1,"severity":"warning","reason":"Each selector in a comma sequence should be on its own line","linter":"SingleLinePerSelector"},{"line":103,"column":1,"length":1,"severity":"warning","reason":"Each selector in a comma sequence should be on its own line","linter":"SingleLinePerSelector"},{"line":104,"column":1,"length":1,"severity":"warning","reason":"Line should be indented with spaces, not tabs","linter":"Indentation"},{"line":104,"column":2,"length":24,"severity":"warning","reason":"Colon after property should be followed by one space","linter":"SpaceAfterPropertyColon"},{"line":105,"column":1,"length":1,"severity":"warning","reason":"Each selector in a comma sequence should be on its own line","linter":"SingleLinePerSelector"},{"line":106,"column":1,"length":1,"severity":"warning","reason":"Each selector in a comma sequence should be on its own line","linter":"SingleLinePerSelector"},{"line":111,"column":1,"length":1,"severity":"warning","reason":"Line should be indented with spaces, not tabs","linter":"Indentation"},{"line":111,"column":2,"length":21,"severity":"warning","reason":"Colon after property should be followed by one space","linter":"SpaceAfterPropertyColon"},{"line":112,"column":1,"length":1,"severity":"warning","reason":"Line should be indented with spaces, not tabs","linter":"Indentation"},{"line":112,"column":2,"length":21,"severity":"warning","reason":"Colon after property should be followed by one space","linter":"SpaceAfterPropertyColon"},{"line":113,"column":1,"length":1,"severity":"warning","reason":"Files should end with a trailing newline","linter":"FinalNewline"}],"UI/SRC/Sass/Shared/_Settings.scss":[{"line":1,"column":1,"length":1,"severity":"warning","reason":"Use `//` comments everywhere","linter":"Comment"},{"line":16,"column":1,"length":1,"severity":"warning","reason":"Declaration should be terminated by a single semicolon","linter":"TrailingSemicolon"},{"line":21,"column":1,"length":1,"severity":"warning","reason":"Files should end with a trailing newline","linter":"FinalNewline"}],"node_modules/gulp-compass/test/bower_components/_base.scss":[{"line":2,"column":9,"length":15,"severity":"warning","reason":"Prefer single quoted strings","linter":"StringQuotes"},{"line":5,"column":1,"length":1,"severity":"warning","reason":"Line should be indented 2 spaces, but was indented 4 spaces","linter":"Indentation"}],"node_modules/gulp-compass/test/bower_components2/_base2.scss":[{"line":1,"column":2,"length":16,"severity":"warning","reason":"Name of variable `foot_color` should be written in all lowercase letters with hyphens instead of underscores","linter":"NameFormat"},{"line":4,"column":1,"length":1,"severity":"warning","reason":"Line should be indented 2 spaces, but was indented 4 spaces","linter":"Indentation"},{"line":4,"column":12,"length":11,"severity":"warning","reason":"Name of variable `foot_color` should be written in all lowercase letters with hyphens instead of underscores","linter":"NameFormat"}],"node_modules/gulp-compass/test/sass/_imported.scss":[{"line":4,"column":5,"length":12,"severity":"warning","reason":"Properties should be ordered family, size, weight","linter":"PropertySortOrder"}],"node_modules/gulp-compass/test/sass/base/compile.scss":[{"line":9,"column":3,"length":7,"severity":"warning","reason":"Colon after property should be followed by one space","linter":"SpaceAfterPropertyColon"},{"line":14,"column":3,"length":20,"severity":"warning","reason":"Properties should be ordered border-color, margin, padding","linter":"PropertySortOrder"}],"node_modules/gulp-compass/test/sass/base/compile2.scss":[{"line":9,"column":3,"length":7,"severity":"warning","reason":"Colon after property should be followed by one space","linter":"SpaceAfterPropertyColon"},{"line":14,"column":3,"length":20,"severity":"warning","reason":"Properties should be ordered border-color, margin, padding","linter":"PropertySortOrder"}],"node_modules/gulp-compass/test/sass/base/compile3.scss":[{"line":9,"column":3,"length":7,"severity":"warning","reason":"Colon after property should be followed by one space","linter":"SpaceAfterPropertyColon"},{"line":14,"column":3,"length":20,"severity":"warning","reason":"Properties should be ordered border-color, margin, padding","linter":"PropertySortOrder"}],"node_modules/gulp-compass/test/sass/compile.scss":[{"line":9,"column":3,"length":7,"severity":"warning","reason":"Colon after property should be followed by one space","linter":"SpaceAfterPropertyColon"},{"line":14,"column":3,"length":20,"severity":"warning","reason":"Properties should be ordered border-color, margin, padding","linter":"PropertySortOrder"}],"node_modules/gulp-compass/test/sass/error.scss":[{"line":3,"column":1,"length":1,"severity":"error","reason":"Syntax Error: Invalid CSS after \"  color: #ccc\": expected \"{\", was \"\""}],"node_modules/gulp-compass/test/sass/import.scss":[{"line":1,"column":9,"length":6,"severity":"warning","reason":"Prefer single quoted strings","linter":"StringQuotes"}],"node_modules/gulp-compass/test/sass/import2.scss":[{"line":1,"column":9,"length":6,"severity":"warning","reason":"Prefer single quoted strings","linter":"StringQuotes"},{"line":2,"column":9,"length":7,"severity":"warning","reason":"Prefer single quoted strings","linter":"StringQuotes"}],"node_modules/gulp-compass/test/sass/multiple-require.scss":[{"line":1,"column":9,"length":6,"severity":"warning","reason":"Prefer single quoted strings","linter":"StringQuotes"},{"line":2,"column":9,"length":15,"severity":"warning","reason":"Prefer single quoted strings","linter":"StringQuotes"}],"node_modules/gulp-compass/test/sass/partial.scss":[{"line":1,"column":9,"length":11,"severity":"warning","reason":"Prefer single quoted strings","linter":"StringQuotes"}],"node_modules/gulp-compass/test/sass/partial/_base_1.scss":[{"line":2,"column":10,"length":4,"severity":"warning","reason":"Color literals like `#fff` should only be used in variable declarations; they should be referred to via variable everywhere else.","linter":"ColorVariable"}],"node_modules/gulp-compass/test/sass/partial/_base_2.scss":[{"line":2,"column":10,"length":4,"severity":"warning","reason":"Color literals like `#000` should only be used in variable declarations; they should be referred to via variable everywhere else.","linter":"ColorVariable"}],"node_modules/gulp-compass/test/sass/require.scss":[{"line":1,"column":9,"length":6,"severity":"warning","reason":"Prefer single quoted strings","linter":"StringQuotes"}],"node_modules/gulp-compass/test/sass/spriting.scss":[{"line":1,"column":9,"length":27,"severity":"warning","reason":"Prefer single quoted strings","linter":"StringQuotes"},{"line":2,"column":9,"length":16,"severity":"warning","reason":"Prefer single quoted strings","linter":"StringQuotes"}],"node_modules/gulp-scss-lint/test/fixtures/invalid-error.scss":[{"line":4,"column":1,"length":1,"severity":"error","reason":"Syntax Error: Invalid CSS after \"}\": expected \"}\", was \"\""}],"node_modules/gulp-scss-lint/test/fixtures/invalid.scss":[{"line":1,"column":1,"length":1,"severity":"warning","reason":"Avoid using id selectors","linter":"IdSelector"},{"line":2,"column":1,"length":1,"severity":"warning","reason":"Line should be indented 2 spaces, but was indented 0 spaces","linter":"Indentation"},{"line":2,"column":1,"length":6,"severity":"warning","reason":"Empty rule","linter":"EmptyRule"},{"line":3,"column":1,"length":1,"severity":"warning","reason":"Files should end with a trailing newline","linter":"FinalNewline"}]}